odoo/addons/passport_expiration/README.rst
odoo/addons/passport_expiration/__init__.py
odoo/addons/passport_expiration/__manifest__.py
odoo/addons/passport_expiration/i18n/fr.po
odoo/addons/passport_expiration/i18n/passport_expiration.pot
odoo/addons/passport_expiration/models/__init__.py
odoo/addons/passport_expiration/models/hr.py
odoo/addons/passport_expiration/readme/CONTRIBUTORS.rst
odoo/addons/passport_expiration/readme/DESCRIPTION.rst
odoo/addons/passport_expiration/readme/USAGE.rst
odoo/addons/passport_expiration/static/description/icon.png
odoo/addons/passport_expiration/static/description/index.html
odoo/addons/passport_expiration/views/hr_view.xml
odoo_addon_passport_expiration-15.0.1.0.0.3.dist-info/METADATA
odoo_addon_passport_expiration-15.0.1.0.0.3.dist-info/WHEEL
odoo_addon_passport_expiration-15.0.1.0.0.3.dist-info/top_level.txt
odoo_addon_passport_expiration-15.0.1.0.0.3.dist-info/RECORD
